README.rst
setup.py
SwiftSeq.egg-info/PKG-INFO
SwiftSeq.egg-info/SOURCES.txt
SwiftSeq.egg-info/dependency_links.txt
SwiftSeq.egg-info/entry_points.txt
SwiftSeq.egg-info/requires.txt
SwiftSeq.egg-info/top_level.txt
swiftseq/__init__.py
swiftseq/core/__init__.py
swiftseq/core/contigs.py
swiftseq/core/exceptions.py
swiftseq/core/input.py
swiftseq/core/readgroups.py
swiftseq/core/workflow.py
swiftseq/core/commands/__init__.py
swiftseq/core/commands/install_env.py
swiftseq/core/commands/restart.py
swiftseq/core/commands/run.py
swiftseq/swift/__init__.py
swiftseq/swift/syntax.py
swiftseq/swift/wrappers.py
swiftseq/swift/config/__init__.py
swiftseq/swift/config/generate.py
swiftseq/swift/generate/__init__.py
swiftseq/util/__init__.py
swiftseq/util/path.py