Metadata-Version: 1.0
Name: SwiftSeq
Version: 1.0.1
Summary: SwiftSeq Parallel Genomics Workflow
Home-page: https://github.com/PittGenomics/SwiftSeq
Author: Jason Pitt
Author-email: jason.j.pitt@gmail.com
License: Apache Software License
Platform: UNKNOWN
